url2rss/__init__.py
url2rss/browser.py
url2rss/core.py
url2rss/detector.py
url2rss/extractor.py
url2rss/renderer.py
url2rss-0.0.2.dist-info/METADATA
url2rss-0.0.2.dist-info/WHEEL
url2rss-0.0.2.dist-info/top_level.txt
url2rss-0.0.2.dist-info/RECORD
