Metadata-Version: 2.4
Name: url2rss
Version: 0.0.2
Summary: A lightweight tool for generating RSS feeds from public URLs, including news pages, search results, and JavaScript-rendered websites.
Author-email: Abdul Ghaffar <abdul@switchfxtech.com>
Maintainer: SwitchFxTech
License: MIT
Project-URL: Homepage, https://github.com/SwitchFX/url2rss
Requires-Python: >=3.10
Requires-Dist: requests
Requires-Dist: beautifulsoup4
Requires-Dist: lxml
Requires-Dist: feedgen
Requires-Dist: playwright
